scenario/__init__.py
scenario/run.py
scenario/example/__init__.py
scenario/example/animate_base_lockdown.py
scenario/example/benchmark_base_lockdown.py
scenario/example/sc0_base_lockdown.py
scenario/example/sc10_variant.py
scenario/example/sc1_simple_lockdown_removal.py
scenario/example/sc2_yoyo_lockdown_removal.py
scenario/example/sc3_loose_lockdown.py
scenario/example/sc4_rogue_citizen.py
scenario/example/sc5_rogue_neighborhood.py
scenario/example/sc6_travelers.py
scenario/example/sc7_nominal_lockdown_removal.py
scenario/example/sc8_innoculation.py
scenario/example/sc9_vaccination.py
scenario/example/scx_base_just_a_flu.py
scenario/helper/__init__.py
scenario/helper/progressbar.py
scenario/helper/progressbar_actor.py
scenario/helper/ray.py
scenario/helper/scenario.py
simulator/__init__.py
simulator/animation.py
simulator/run.py
simulator/run_benchmark.py
simulator/constants/__init__.py
simulator/constants/keys.py
simulator/constants/parameters.py
simulator/helper/__init__.py
simulator/helper/dynamic.py
simulator/helper/environment.py
simulator/helper/parser.py
simulator/helper/plot.py
simulator/helper/simulation.py
simulator/helper/utils.py
tests/helper/__init__.py
tests/helper/helpers_test.py
tests/scenario/__init__.py
tests/scenario/examples_test.py
tests/simulator/__init__.py
tests/simulator/day_incrementation_test.py
tests/simulator/environment_test.py
tests/simulator/house_propagation_test.py
tests/simulator/plot_test.py
tests/simulator/simulator_test.py
tests/simulator/store_propagation_test.py
tests/simulator/transport_propagation_test.py
tests/simulator/workplace_propagation_test.py
pandemic_simulation-0.2.0.dist-info/LICENSE
pandemic_simulation-0.2.0.dist-info/METADATA
pandemic_simulation-0.2.0.dist-info/WHEEL
pandemic_simulation-0.2.0.dist-info/top_level.txt
pandemic_simulation-0.2.0.dist-info/RECORD
