Metadata-Version: 2.1
Name: pandemic-simulation
Version: 0.2.0
Summary: "Life simulation" of a SEIR inspired model to better understand pandemic using python
Home-page: https://github.com/AshtonIzmev
License: MIT License
Platform: UNKNOWN
Requires-Python: >=3.6
Requires-Dist: pandas
Requires-Dist: scipy
Requires-Dist: numpy
Requires-Dist: argparse
Requires-Dist: sklearn
Requires-Dist: matplotlib
Requires-Dist: seaborn
